gcp_cloud_logger/__init__.py
gcp_cloud_logger/core/__init__.py
gcp_cloud_logger/core/cloud_logger.py
gcp_cloud_logger-0.2.4.dist-info/LICENSE
gcp_cloud_logger-0.2.4.dist-info/METADATA
gcp_cloud_logger-0.2.4.dist-info/WHEEL
gcp_cloud_logger-0.2.4.dist-info/top_level.txt
gcp_cloud_logger-0.2.4.dist-info/RECORD
