Metadata-Version: 2.1
Name: gcp-cloud-logger
Version: 0.2.4
Summary: Google Cloud Platform logging package
Home-page: https://github.com/turisesonia/gcp_cloud_logger
Author: Sam Yao
Author-email: turisesonia@gmail.com
License: UNKNOWN
Platform: UNKNOWN
Classifier: Programming Language :: Python :: 3
Classifier: License :: OSI Approved :: MIT License
Classifier: Operating System :: OS Independent
Requires-Python: >=3.6
Requires-Dist: google-cloud-logging
Requires-Dist: ujson
